importlinter/__init__.py
importlinter/api.py
importlinter/cli.py
importlinter/configuration.py
importlinter/py.typed
importlinter/adapters/__init__.py
importlinter/adapters/building.py
importlinter/adapters/filesystem.py
importlinter/adapters/timing.py
importlinter/adapters/user_options.py
importlinter/application/__init__.py
importlinter/application/app_config.py
importlinter/application/contract_utils.py
importlinter/application/file_finding.py
importlinter/application/output.py
importlinter/application/rendering.py
importlinter/application/sentinels.py
importlinter/application/use_cases.py
importlinter/application/user_options.py
importlinter/application/ports/__init__.py
importlinter/application/ports/building.py
importlinter/application/ports/filesystem.py
importlinter/application/ports/reporting.py
importlinter/application/ports/timing.py
importlinter/application/ports/user_options.py
importlinter/contracts/__init__.py
importlinter/contracts/_common.py
importlinter/contracts/acyclic_siblings.py
importlinter/contracts/forbidden.py
importlinter/contracts/independence.py
importlinter/contracts/layers.py
importlinter/contracts/protected.py
importlinter/domain/__init__.py
importlinter/domain/contract.py
importlinter/domain/fields.py
importlinter/domain/helpers.py
importlinter/domain/imports.py
import_linter-2.7.dist-info/METADATA
import_linter-2.7.dist-info/WHEEL
import_linter-2.7.dist-info/entry_points.txt
import_linter-2.7.dist-info/licenses/AUTHORS.rst
import_linter-2.7.dist-info/licenses/LICENSE
import_linter-2.7.dist-info/RECORD
