Metadata-Version: 2.4
Name: import-linter
Version: 2.7
Summary: Enforces rules for the imports within and between Python packages.
Project-URL: Documentation, https://import-linter.readthedocs.io/
Project-URL: Source-code, https://github.com/seddonym/import-linter/
Author-email: David Seddon <david@seddonym.me>
License: BSD 2-Clause License
License-File: AUTHORS.rst
License-File: LICENSE
Classifier: Development Status :: 5 - Production/Stable
Classifier: Intended Audience :: Developers
Classifier: License :: OSI Approved :: BSD License
Classifier: Operating System :: Microsoft :: Windows
Classifier: Operating System :: POSIX
Classifier: Operating System :: Unix
Classifier: Programming Language :: Python
Classifier: Programming Language :: Python :: 3.10
Classifier: Programming Language :: Python :: 3.11
Classifier: Programming Language :: Python :: 3.12
Classifier: Programming Language :: Python :: 3.13
Classifier: Programming Language :: Python :: 3.14
Classifier: Programming Language :: Python :: Implementation :: CPython
Classifier: Topic :: Utilities
Requires-Python: >=3.10
Requires-Dist: click>=6
Requires-Dist: grimp==3.13
Requires-Dist: rich>=14.2.0
Requires-Dist: tomli>=1.2.1; python_version < '3.11'
Requires-Dist: typing-extensions>=3.10.0.0
